uv_blank_template/__init__.py
uv_blank_template/__main__.py
uv_blank_template-0.0.18.dist-info/WHEEL
uv_blank_template-0.0.18.dist-info/entry_points.txt
uv_blank_template-0.0.18.dist-info/METADATA
uv_blank_template-0.0.18.dist-info/RECORD
